idoit_api_client/__init__.py
idoit_api_client/cli.py
idoit_api_client/cmdbcategory.py
idoit_api_client/cmdbcategoryinfo.py
idoit_api_client/cmdbobject.py
idoit_api_client/cmdbobjects.py
idoit_api_client/cmdbobjecttypecategories.py
idoit_api_client/cmdbobjecttypes.py
idoit_api_client-0.1.0.dist-info/AUTHORS.rst
idoit_api_client-0.1.0.dist-info/LICENSE
idoit_api_client-0.1.0.dist-info/METADATA
idoit_api_client-0.1.0.dist-info/WHEEL
idoit_api_client-0.1.0.dist-info/entry_points.txt
idoit_api_client-0.1.0.dist-info/top_level.txt
idoit_api_client-0.1.0.dist-info/RECORD
